oilfox.py
oilfoxpy-0.4.dist-info/LICENSE
oilfoxpy-0.4.dist-info/METADATA
oilfoxpy-0.4.dist-info/WHEEL
oilfoxpy-0.4.dist-info/top_level.txt
oilfoxpy-0.4.dist-info/RECORD
