Metadata-Version: 2.1
Name: oilfoxpy
Version: 0.4
Summary: API call to oilfox
Home-page: https://github.com/ITTV-tools/olifoxpy
Author: ittv-tools
Author-email: UNKNOWN
License: UNKNOWN
Platform: UNKNOWN
Requires-Dist: jwt
Requires-Dist: requests
